<?xml version="1.0" encoding="UTF-8" ?>
<Module>
  <ModulePrefs
    title="AC-useful-links.xml"
    description="">
    <!--<Require feature="idi"/>-->
    <!--<Require feature="locked-domain" />-->
	  <!--<Require feature="dynamic-height"/>-->
	  <!--<Require feature="setprefs" />-->
  </ModulePrefs>

  <UserPref
    name="spreadsheetKey"
    default_value=""
    display_name="spreadsheetKey (example: 1hZ2TFoq3ihf7d9lVT7hx3P3cSui7kaG5s7zR781GnL8)"
    required="false"
  />

  <Content view="canvas" preferred_height="200px">
    <![CDATA[
      <script src="https://www.google.com/jsapi" type="text/javascript"></script>
      <script src="https://cdn.rawgit.com/sopraux/gsites/v1.0/evolucionaDigital/js/jquery.min.js" type="text/javascript"></script>
      <script src="https://cdn.rawgit.com/sopraux/gsites/v1.0/gsites-components/js/functionHelpers.js" type="text/javascript"></script>

      <style type="text/css">
        /* @group fonts */
        @font-face {
          font-family: 'BBVA Web Light';
          src:url('https://cdn.rawgit.com/sopraux/gsites/v1.0/actividadtyc/fonts/web-light/web-light.eot');
          src:url('https://cdn.rawgit.com/sopraux/gsites/v1.0/actividadtyc/fonts/web-light/web-light.eot?iefix') format("embedded-opentype"),
            url('https://cdn.rawgit.com/sopraux/gsites/v1.0/actividadtyc/fonts/web-light/web-light.woff') format("woff"),
            url('https://cdn.rawgit.com/sopraux/gsites/v1.0/actividadtyc/fonts/web-light/web-light.ttf') format("truetype"),
            url('https://cdn.rawgit.com/sopraux/gsites/v1.0/actividadtyc/fonts/web-light/web-light.svg#BBVA Web Light') format("svg");
          font-style: normal;
          font-weight: normal;
        }

        @font-face {
          font-family: 'BBVA Web Book';
          src:url('https://cdn.rawgit.com/sopraux/gsites/v1.0/actividadtyc/fonts/web-book/web-book.eot');
          src:url('https://cdn.rawgit.com/sopraux/gsites/v1.0/actividadtyc/fonts/web-book/web-book.eot?iefix') format("embedded-opentype"),
            url('https://cdn.rawgit.com/sopraux/gsites/v1.0/actividadtyc/fonts/web-book/web-book.woff') format("woff"),
            url('https://cdn.rawgit.com/sopraux/gsites/v1.0/actividadtyc/fonts/web-book/web-book.ttf') format("truetype"),
            url('https://cdn.rawgit.com/sopraux/gsites/v1.0/actividadtyc/fonts/web-book/web-book.svg#BBVA Web Book') format("svg");
          font-style: normal;
          font-weight: normal;
        }

        @font-face {
          font-family: 'BBVA Web Medium';
          src:url('https://cdn.rawgit.com/sopraux/gsites/v1.0/actividadtyc/fonts/web-medium/web-medium.eot');
          src:url('https://cdn.rawgit.com/sopraux/gsites/v1.0/actividadtyc/fonts/web-medium/web-medium.eot?iefix') format("embedded-opentype"),
            url('https://cdn.rawgit.com/sopraux/gsites/v1.0/actividadtyc/fonts/web-medium/web-medium.woff') format("woff"),
            url('https://cdn.rawgit.com/sopraux/gsites/v1.0/actividadtyc/fonts/web-medium/web-medium.ttf') format("truetype"),
            url('https://cdn.rawgit.com/sopraux/gsites/v1.0/actividadtyc/fonts/web-medium/web-medium.svg#BBVA Web Medium') format("svg");
          font-style: normal;
          font-weight: normal;
        }
        /* @end */

        .clearfix {
          overflow: auto;
        }

        .container {
          font-family: arial, sans-serif;
          font-size: 12px;
          margin-bottom: 16px;
          position: relative;
          width: 884px;
          margin: 7px;
          float: left;
        }

        h2 {
          font-family: BBVA Web Light;
          font-size: 18px;
          color: #000;
          padding-bottom: 10px;
          border-bottom: 1px solid #e5e5e5;
          margin-bottom: 30px;
        }

        .link-wrapper {
          margin-bottom: 10px;
        }

        .link {
          display: inline-block;
          font-size: 12px;
          font-family: arial;
          color: #1e6bb3 !important;
          text-decoration: none;
        }
      </style>

      <div class="container" id="container">
        <h2>Enlaces de interés</h2>
        <div id="useful-links-list"></div>
      </div>

      <script type="text/javascript">

        // adjustGadgetHeight('container');
        // var gadgetHelper = null;
        google.load('visualization', '1', {packages: ['table']});
        google.setOnLoadCallback(sendQuery);
        var prefs = new gadgets.Prefs();

        function sendQuery(){
          var spreadsheetKey = prefs.getString('spreadsheetKey');
          var sheetName = encodeURIComponent('links');
          var queryString = encodeURIComponent('SELECT *');
          var query = new google.visualization.Query('https://spreadsheets.google.com/tq?key=' + spreadsheetKey + '&sheet=' + sheetName + '&tq=' + queryString);
          query.send(function (response) { handleQueryResponse(response); });
        }

        function handleQueryResponse(response) {
          var data = response.getDataTable();
          var rows = data.getNumberOfRows();

          var html = '';
          for (var i = 0; i < rows; i++) {
            var link = data.getFormattedValue(i, 0);
            var href = data.getFormattedValue(i, 1);
            html += '<div class="link-wrapper"><a class="link" href="' + href + '" target="_blank">' + link + '</a></div>';
          }

          document
            .getElementById('useful-links-list')
            .innerHTML = html;

          try {
            gadgets.window.adjustHeight();
          } catch(err) {
            console.error(err);
          }
        }

      </script>
    ]]>
  </Content>

</Module>
